{"ID":"abea13ab-cc53-4732-9296-e92353fc6c43","DefinitionID":11876533,"UserID":"e3afd26a-5019-4b33-ac77-a6886276f8a5","WordID":"9ccbfc03-e4e5-45bf-bab0-6c052a4e4152","Definition":"Huxtable (Cosby)\rThe subtle art of taking a huge crap, placing it in your freezer until under 30 degrees fahrenheit. Once frozen, remove it from the freezer and hide it somewhere near your bed. Start having anal sex with your partner(female) and slide it into her vagina before she can react to the chill, but while you nut. It'll melt, completing the maneuver.","ThumbsDown":0,"ThumbsUp":2,"DatePosted":"2017-08-14T00:00:00","Rank":1}